{
  "resolvedId": "/home/zepor/ssweb/frontend-container/node_modules/highlight.js/lib/languages/groovy.js",
  "transforms": [
    {
      "name": "vite:load-fallback",
      "result": "/**\n * @param {string} value\n * @returns {RegExp}\n * */\n\n/**\n * @param {RegExp | string } re\n * @returns {string}\n */\nfunction source(re) {\n  if (!re) return null;\n  if (typeof re === \"string\") return re;\n\n  return re.source;\n}\n\n/**\n * @param {RegExp | string } re\n * @returns {string}\n */\nfunction lookahead(re) {\n  return concat('(?=', re, ')');\n}\n\n/**\n * @param {...(RegExp | string) } args\n * @returns {string}\n */\nfunction concat(...args) {\n  const joined = args.map((x) => source(x)).join(\"\");\n  return joined;\n}\n\n/*\n Language: Groovy\n Author: Guillaume Laforge <glaforge@gmail.com>\n Description: Groovy programming language implementation inspired from Vsevolod's Java mode\n Website: https://groovy-lang.org\n */\n\nfunction variants(variants, obj = {}) {\n  obj.variants = variants;\n  return obj;\n}\n\nfunction groovy(hljs) {\n  const IDENT_RE = '[A-Za-z0-9_$]+';\n  const COMMENT = variants([\n    hljs.C_LINE_COMMENT_MODE,\n    hljs.C_BLOCK_COMMENT_MODE,\n    hljs.COMMENT(\n      '/\\\\*\\\\*',\n      '\\\\*/',\n      {\n        relevance: 0,\n        contains: [\n          {\n            // eat up @'s in emails to prevent them to be recognized as doctags\n            begin: /\\w+@/,\n            relevance: 0\n          },\n          {\n            className: 'doctag',\n            begin: '@[A-Za-z]+'\n          }\n        ]\n      }\n    )\n  ]);\n  const REGEXP = {\n    className: 'regexp',\n    begin: /~?\\/[^\\/\\n]+\\//,\n    contains: [ hljs.BACKSLASH_ESCAPE ]\n  };\n  const NUMBER = variants([\n    hljs.BINARY_NUMBER_MODE,\n    hljs.C_NUMBER_MODE\n  ]);\n  const STRING = variants([\n    {\n      begin: /\"\"\"/,\n      end: /\"\"\"/\n    },\n    {\n      begin: /'''/,\n      end: /'''/\n    },\n    {\n      begin: \"\\\\$/\",\n      end: \"/\\\\$\",\n      relevance: 10\n    },\n    hljs.APOS_STRING_MODE,\n    hljs.QUOTE_STRING_MODE\n  ],\n  {\n    className: \"string\"\n  }\n  );\n\n  return {\n    name: 'Groovy',\n    keywords: {\n      built_in: 'this super',\n      literal: 'true false null',\n      keyword:\n            'byte short char int long boolean float double void ' +\n            // groovy specific keywords\n            'def as in assert trait ' +\n            // common keywords with Java\n            'abstract static volatile transient public private protected synchronized final ' +\n            'class interface enum if else for while switch case break default continue ' +\n            'throw throws try catch finally implements extends new import package return instanceof'\n    },\n    contains: [\n      hljs.SHEBANG({\n        binary: \"groovy\",\n        relevance: 10\n      }),\n      COMMENT,\n      STRING,\n      REGEXP,\n      NUMBER,\n      {\n        className: 'class',\n        beginKeywords: 'class interface trait enum',\n        end: /\\{/,\n        illegal: ':',\n        contains: [\n          {\n            beginKeywords: 'extends implements'\n          },\n          hljs.UNDERSCORE_TITLE_MODE\n        ]\n      },\n      {\n        className: 'meta',\n        begin: '@[A-Za-z]+',\n        relevance: 0\n      },\n      {\n        // highlight map keys and named parameters as attrs\n        className: 'attr',\n        begin: IDENT_RE + '[ \\t]*:',\n        relevance: 0\n      },\n      {\n        // catch middle element of the ternary operator\n        // to avoid highlight it as a label, named parameter, or map key\n        begin: /\\?/,\n        end: /:/,\n        relevance: 0,\n        contains: [\n          COMMENT,\n          STRING,\n          REGEXP,\n          NUMBER,\n          'self'\n        ]\n      },\n      {\n        // highlight labeled statements\n        className: 'symbol',\n        begin: '^[ \\t]*' + lookahead(IDENT_RE + ':'),\n        excludeBegin: true,\n        end: IDENT_RE + ':',\n        relevance: 0\n      }\n    ],\n    illegal: /#|<\\//\n  };\n}\n\nmodule.exports = groovy;\n",
      "start": 1702937444336,
      "end": 1702937444376,
      "sourcemaps": null
    },
    {
      "name": "vite:react-babel",
      "start": 1702937444376,
      "end": 1702937444376,
      "order": "pre"
    },
    {
      "name": "vite:css",
      "start": 1702937444376,
      "end": 1702937444376,
      "order": "normal"
    },
    {
      "name": "vite:esbuild",
      "start": 1702937444376,
      "end": 1702937444376,
      "order": "normal"
    },
    {
      "name": "vite:json",
      "start": 1702937444376,
      "end": 1702937444376,
      "order": "normal"
    },
    {
      "name": "vite:worker",
      "start": 1702937444376,
      "end": 1702937444376,
      "order": "normal"
    },
    {
      "name": "vite:define",
      "start": 1702937444376,
      "end": 1702937444376,
      "order": "normal"
    },
    {
      "name": "vite:css-post",
      "start": 1702937444376,
      "end": 1702937444376,
      "order": "normal"
    },
    {
      "name": "vite:build-html",
      "start": 1702937444376,
      "end": 1702937444376,
      "order": "normal"
    },
    {
      "name": "vite:worker-import-meta-url",
      "start": 1702937444376,
      "end": 1702937444376,
      "order": "normal"
    },
    {
      "name": "vite:asset-import-meta-url",
      "start": 1702937444376,
      "end": 1702937444376,
      "order": "normal"
    },
    {
      "name": "commonjs",
      "result": "/**\n * @param {string} value\n * @returns {RegExp}\n * */\nimport * as commonjsHelpers from \"\u0000commonjsHelpers.js\";\n\nvar groovy_1;\nvar hasRequiredGroovy;\n\nfunction requireGroovy () {\n\tif (hasRequiredGroovy) return groovy_1;\n\thasRequiredGroovy = 1;\n\t/**\n\t * @param {RegExp | string } re\n\t * @returns {string}\n\t */\n\tfunction source(re) {\n\t  if (!re) return null;\n\t  if (typeof re === \"string\") return re;\n\n\t  return re.source;\n\t}\n\n\t/**\n\t * @param {RegExp | string } re\n\t * @returns {string}\n\t */\n\tfunction lookahead(re) {\n\t  return concat('(?=', re, ')');\n\t}\n\n\t/**\n\t * @param {...(RegExp | string) } args\n\t * @returns {string}\n\t */\n\tfunction concat(...args) {\n\t  const joined = args.map((x) => source(x)).join(\"\");\n\t  return joined;\n\t}\n\n\t/*\n\t Language: Groovy\n\t Author: Guillaume Laforge <glaforge@gmail.com>\n\t Description: Groovy programming language implementation inspired from Vsevolod's Java mode\n\t Website: https://groovy-lang.org\n\t */\n\n\tfunction variants(variants, obj = {}) {\n\t  obj.variants = variants;\n\t  return obj;\n\t}\n\n\tfunction groovy(hljs) {\n\t  const IDENT_RE = '[A-Za-z0-9_$]+';\n\t  const COMMENT = variants([\n\t    hljs.C_LINE_COMMENT_MODE,\n\t    hljs.C_BLOCK_COMMENT_MODE,\n\t    hljs.COMMENT(\n\t      '/\\\\*\\\\*',\n\t      '\\\\*/',\n\t      {\n\t        relevance: 0,\n\t        contains: [\n\t          {\n\t            // eat up @'s in emails to prevent them to be recognized as doctags\n\t            begin: /\\w+@/,\n\t            relevance: 0\n\t          },\n\t          {\n\t            className: 'doctag',\n\t            begin: '@[A-Za-z]+'\n\t          }\n\t        ]\n\t      }\n\t    )\n\t  ]);\n\t  const REGEXP = {\n\t    className: 'regexp',\n\t    begin: /~?\\/[^\\/\\n]+\\//,\n\t    contains: [ hljs.BACKSLASH_ESCAPE ]\n\t  };\n\t  const NUMBER = variants([\n\t    hljs.BINARY_NUMBER_MODE,\n\t    hljs.C_NUMBER_MODE\n\t  ]);\n\t  const STRING = variants([\n\t    {\n\t      begin: /\"\"\"/,\n\t      end: /\"\"\"/\n\t    },\n\t    {\n\t      begin: /'''/,\n\t      end: /'''/\n\t    },\n\t    {\n\t      begin: \"\\\\$/\",\n\t      end: \"/\\\\$\",\n\t      relevance: 10\n\t    },\n\t    hljs.APOS_STRING_MODE,\n\t    hljs.QUOTE_STRING_MODE\n\t  ],\n\t  {\n\t    className: \"string\"\n\t  }\n\t  );\n\n\t  return {\n\t    name: 'Groovy',\n\t    keywords: {\n\t      built_in: 'this super',\n\t      literal: 'true false null',\n\t      keyword:\n\t            'byte short char int long boolean float double void ' +\n\t            // groovy specific keywords\n\t            'def as in assert trait ' +\n\t            // common keywords with Java\n\t            'abstract static volatile transient public private protected synchronized final ' +\n\t            'class interface enum if else for while switch case break default continue ' +\n\t            'throw throws try catch finally implements extends new import package return instanceof'\n\t    },\n\t    contains: [\n\t      hljs.SHEBANG({\n\t        binary: \"groovy\",\n\t        relevance: 10\n\t      }),\n\t      COMMENT,\n\t      STRING,\n\t      REGEXP,\n\t      NUMBER,\n\t      {\n\t        className: 'class',\n\t        beginKeywords: 'class interface trait enum',\n\t        end: /\\{/,\n\t        illegal: ':',\n\t        contains: [\n\t          {\n\t            beginKeywords: 'extends implements'\n\t          },\n\t          hljs.UNDERSCORE_TITLE_MODE\n\t        ]\n\t      },\n\t      {\n\t        className: 'meta',\n\t        begin: '@[A-Za-z]+',\n\t        relevance: 0\n\t      },\n\t      {\n\t        // highlight map keys and named parameters as attrs\n\t        className: 'attr',\n\t        begin: IDENT_RE + '[ \\t]*:',\n\t        relevance: 0\n\t      },\n\t      {\n\t        // catch middle element of the ternary operator\n\t        // to avoid highlight it as a label, named parameter, or map key\n\t        begin: /\\?/,\n\t        end: /:/,\n\t        relevance: 0,\n\t        contains: [\n\t          COMMENT,\n\t          STRING,\n\t          REGEXP,\n\t          NUMBER,\n\t          'self'\n\t        ]\n\t      },\n\t      {\n\t        // highlight labeled statements\n\t        className: 'symbol',\n\t        begin: '^[ \\t]*' + lookahead(IDENT_RE + ':'),\n\t        excludeBegin: true,\n\t        end: IDENT_RE + ':',\n\t        relevance: 0\n\t      }\n\t    ],\n\t    illegal: /#|<\\//\n\t  };\n\t}\n\n\tgroovy_1 = groovy;\n\treturn groovy_1;\n}\n\nexport { requireGroovy as __require };",
      "start": 1702937444376,
      "end": 1702937444376,
      "order": "normal",
      "sourcemaps": {
        "version": 3,
        "sources": [
          ""
        ],
        "names": [],
        "mappings": ";;;;;;;;;;;;CAKA;CACA;CACA;CACA;CACA,SAAS,MAAM,CAAC,EAAE,EAAE;CACpB,EAAE,IAAI,CAAC,EAAE,EAAE,OAAO,IAAI,CAAC;CACvB,EAAE,IAAI,OAAO,EAAE,KAAK,QAAQ,EAAE,OAAO,EAAE,CAAC;AACxC;CACA,EAAE,OAAO,EAAE,CAAC,MAAM,CAAC;CACnB,CAAC;AACD;CACA;CACA;CACA;CACA;CACA,SAAS,SAAS,CAAC,EAAE,EAAE;CACvB,EAAE,OAAO,MAAM,CAAC,KAAK,EAAE,EAAE,EAAE,GAAG,CAAC,CAAC;CAChC,CAAC;AACD;CACA;CACA;CACA;CACA;CACA,SAAS,MAAM,CAAC,GAAG,IAAI,EAAE;CACzB,EAAE,MAAM,MAAM,GAAG,IAAI,CAAC,GAAG,CAAC,CAAC,CAAC,KAAK,MAAM,CAAC,CAAC,CAAC,CAAC,CAAC,IAAI,CAAC,EAAE,CAAC,CAAC;CACrD,EAAE,OAAO,MAAM,CAAC;CAChB,CAAC;AACD;CACA;CACA;CACA;CACA;CACA;CACA;AACA;CACA,SAAS,QAAQ,CAAC,QAAQ,EAAE,GAAG,GAAG,EAAE,EAAE;CACtC,EAAE,GAAG,CAAC,QAAQ,GAAG,QAAQ,CAAC;CAC1B,EAAE,OAAO,GAAG,CAAC;CACb,CAAC;AACD;CACA,SAAS,MAAM,CAAC,IAAI,EAAE;CACtB,EAAE,MAAM,QAAQ,GAAG,gBAAgB,CAAC;CACpC,EAAE,MAAM,OAAO,GAAG,QAAQ,CAAC;CAC3B,IAAI,IAAI,CAAC,mBAAmB;CAC5B,IAAI,IAAI,CAAC,oBAAoB;CAC7B,IAAI,IAAI,CAAC,OAAO;CAChB,MAAM,SAAS;CACf,MAAM,MAAM;CACZ,MAAM;CACN,QAAQ,SAAS,EAAE,CAAC;CACpB,QAAQ,QAAQ,EAAE;CAClB,UAAU;CACV;CACA,YAAY,KAAK,EAAE,MAAM;CACzB,YAAY,SAAS,EAAE,CAAC;CACxB,WAAW;CACX,UAAU;CACV,YAAY,SAAS,EAAE,QAAQ;CAC/B,YAAY,KAAK,EAAE,YAAY;CAC/B,WAAW;CACX,SAAS;CACT,OAAO;CACP,KAAK;CACL,GAAG,CAAC,CAAC;CACL,EAAE,MAAM,MAAM,GAAG;CACjB,IAAI,SAAS,EAAE,QAAQ;CACvB,IAAI,KAAK,EAAE,gBAAgB;CAC3B,IAAI,QAAQ,EAAE,EAAE,IAAI,CAAC,gBAAgB,EAAE;CACvC,GAAG,CAAC;CACJ,EAAE,MAAM,MAAM,GAAG,QAAQ,CAAC;CAC1B,IAAI,IAAI,CAAC,kBAAkB;CAC3B,IAAI,IAAI,CAAC,aAAa;CACtB,GAAG,CAAC,CAAC;CACL,EAAE,MAAM,MAAM,GAAG,QAAQ,CAAC;CAC1B,IAAI;CACJ,MAAM,KAAK,EAAE,KAAK;CAClB,MAAM,GAAG,EAAE,KAAK;CAChB,KAAK;CACL,IAAI;CACJ,MAAM,KAAK,EAAE,KAAK;CAClB,MAAM,GAAG,EAAE,KAAK;CAChB,KAAK;CACL,IAAI;CACJ,MAAM,KAAK,EAAE,MAAM;CACnB,MAAM,GAAG,EAAE,MAAM;CACjB,MAAM,SAAS,EAAE,EAAE;CACnB,KAAK;CACL,IAAI,IAAI,CAAC,gBAAgB;CACzB,IAAI,IAAI,CAAC,iBAAiB;CAC1B,GAAG;CACH,EAAE;CACF,IAAI,SAAS,EAAE,QAAQ;CACvB,GAAG;CACH,GAAG,CAAC;AACJ;CACA,EAAE,OAAO;CACT,IAAI,IAAI,EAAE,QAAQ;CAClB,IAAI,QAAQ,EAAE;CACd,MAAM,QAAQ,EAAE,YAAY;CAC5B,MAAM,OAAO,EAAE,iBAAiB;CAChC,MAAM,OAAO;CACb,YAAY,qDAAqD;CACjE;CACA,YAAY,yBAAyB;CACrC;CACA,YAAY,iFAAiF;CAC7F,YAAY,4EAA4E;CACxF,YAAY,wFAAwF;CACpG,KAAK;CACL,IAAI,QAAQ,EAAE;CACd,MAAM,IAAI,CAAC,OAAO,CAAC;CACnB,QAAQ,MAAM,EAAE,QAAQ;CACxB,QAAQ,SAAS,EAAE,EAAE;CACrB,OAAO,CAAC;CACR,MAAM,OAAO;CACb,MAAM,MAAM;CACZ,MAAM,MAAM;CACZ,MAAM,MAAM;CACZ,MAAM;CACN,QAAQ,SAAS,EAAE,OAAO;CAC1B,QAAQ,aAAa,EAAE,4BAA4B;CACnD,QAAQ,GAAG,EAAE,IAAI;CACjB,QAAQ,OAAO,EAAE,GAAG;CACpB,QAAQ,QAAQ,EAAE;CAClB,UAAU;CACV,YAAY,aAAa,EAAE,oBAAoB;CAC/C,WAAW;CACX,UAAU,IAAI,CAAC,qBAAqB;CACpC,SAAS;CACT,OAAO;CACP,MAAM;CACN,QAAQ,SAAS,EAAE,MAAM;CACzB,QAAQ,KAAK,EAAE,YAAY;CAC3B,QAAQ,SAAS,EAAE,CAAC;CACpB,OAAO;CACP,MAAM;CACN;CACA,QAAQ,SAAS,EAAE,MAAM;CACzB,QAAQ,KAAK,EAAE,QAAQ,GAAG,SAAS;CACnC,QAAQ,SAAS,EAAE,CAAC;CACpB,OAAO;CACP,MAAM;CACN;CACA;CACA,QAAQ,KAAK,EAAE,IAAI;CACnB,QAAQ,GAAG,EAAE,GAAG;CAChB,QAAQ,SAAS,EAAE,CAAC;CACpB,QAAQ,QAAQ,EAAE;CAClB,UAAU,OAAO;CACjB,UAAU,MAAM;CAChB,UAAU,MAAM;CAChB,UAAU,MAAM;CAChB,UAAU,MAAM;CAChB,SAAS;CACT,OAAO;CACP,MAAM;CACN;CACA,QAAQ,SAAS,EAAE,QAAQ;CAC3B,QAAQ,KAAK,EAAE,SAAS,GAAG,SAAS,CAAC,QAAQ,GAAG,GAAG,CAAC;CACpD,QAAQ,YAAY,EAAE,IAAI;CAC1B,QAAQ,GAAG,EAAE,QAAQ,GAAG,GAAG;CAC3B,QAAQ,SAAS,EAAE,CAAC;CACpB,OAAO;CACP,KAAK;CACL,IAAI,OAAO,EAAE,OAAO;CACpB,GAAG,CAAC;CACJ,CAAC;AACD;AACA,SAAc,GAAG,MAAM"
      }
    },
    {
      "name": "inject",
      "start": 1702937444376,
      "end": 1702937444376,
      "order": "normal"
    },
    {
      "name": "vite:dynamic-import-vars",
      "start": 1702937444376,
      "end": 1702937444376,
      "order": "normal"
    },
    {
      "name": "vite:import-glob",
      "start": 1702937444376,
      "end": 1702937444376,
      "order": "normal"
    },
    {
      "name": "vite:build-import-analysis",
      "start": 1702937444376,
      "end": 1702937444376,
      "order": "normal"
    },
    {
      "name": "vite:reporter",
      "start": 1702937444376,
      "end": 1702937444376,
      "order": "normal"
    }
  ]
}
