{
  "resolvedId": "/home/zepor/ssweb/frontend-container/node_modules/property-expr/index.js",
  "transforms": [
    {
      "name": "vite:load-fallback",
      "result": "/**\n * Based on Kendo UI Core expression code <https://github.com/telerik/kendo-ui-core#license-information>\n */\n'use strict'\n\nfunction Cache(maxSize) {\n  this._maxSize = maxSize\n  this.clear()\n}\nCache.prototype.clear = function () {\n  this._size = 0\n  this._values = Object.create(null)\n}\nCache.prototype.get = function (key) {\n  return this._values[key]\n}\nCache.prototype.set = function (key, value) {\n  this._size >= this._maxSize && this.clear()\n  if (!(key in this._values)) this._size++\n\n  return (this._values[key] = value)\n}\n\nvar SPLIT_REGEX = /[^.^\\]^[]+|(?=\\[\\]|\\.\\.)/g,\n  DIGIT_REGEX = /^\\d+$/,\n  LEAD_DIGIT_REGEX = /^\\d/,\n  SPEC_CHAR_REGEX = /[~`!#$%\\^&*+=\\-\\[\\]\\\\';,/{}|\\\\\":<>\\?]/g,\n  CLEAN_QUOTES_REGEX = /^\\s*(['\"]?)(.*?)(\\1)\\s*$/,\n  MAX_CACHE_SIZE = 512\n\nvar pathCache = new Cache(MAX_CACHE_SIZE),\n  setCache = new Cache(MAX_CACHE_SIZE),\n  getCache = new Cache(MAX_CACHE_SIZE)\n\nvar config\n\nmodule.exports = {\n  Cache: Cache,\n\n  split: split,\n\n  normalizePath: normalizePath,\n\n  setter: function (path) {\n    var parts = normalizePath(path)\n\n    return (\n      setCache.get(path) ||\n      setCache.set(path, function setter(obj, value) {\n        var index = 0\n        var len = parts.length\n        var data = obj\n\n        while (index < len - 1) {\n          var part = parts[index]\n          if (\n            part === '__proto__' ||\n            part === 'constructor' ||\n            part === 'prototype'\n          ) {\n            return obj\n          }\n\n          data = data[parts[index++]]\n        }\n        data[parts[index]] = value\n      })\n    )\n  },\n\n  getter: function (path, safe) {\n    var parts = normalizePath(path)\n    return (\n      getCache.get(path) ||\n      getCache.set(path, function getter(data) {\n        var index = 0,\n          len = parts.length\n        while (index < len) {\n          if (data != null || !safe) data = data[parts[index++]]\n          else return\n        }\n        return data\n      })\n    )\n  },\n\n  join: function (segments) {\n    return segments.reduce(function (path, part) {\n      return (\n        path +\n        (isQuoted(part) || DIGIT_REGEX.test(part)\n          ? '[' + part + ']'\n          : (path ? '.' : '') + part)\n      )\n    }, '')\n  },\n\n  forEach: function (path, cb, thisArg) {\n    forEach(Array.isArray(path) ? path : split(path), cb, thisArg)\n  },\n}\n\nfunction normalizePath(path) {\n  return (\n    pathCache.get(path) ||\n    pathCache.set(\n      path,\n      split(path).map(function (part) {\n        return part.replace(CLEAN_QUOTES_REGEX, '$2')\n      })\n    )\n  )\n}\n\nfunction split(path) {\n  return path.match(SPLIT_REGEX) || ['']\n}\n\nfunction forEach(parts, iter, thisArg) {\n  var len = parts.length,\n    part,\n    idx,\n    isArray,\n    isBracket\n\n  for (idx = 0; idx < len; idx++) {\n    part = parts[idx]\n\n    if (part) {\n      if (shouldBeQuoted(part)) {\n        part = '\"' + part + '\"'\n      }\n\n      isBracket = isQuoted(part)\n      isArray = !isBracket && /^\\d+$/.test(part)\n\n      iter.call(thisArg, part, isBracket, isArray, idx, parts)\n    }\n  }\n}\n\nfunction isQuoted(str) {\n  return (\n    typeof str === 'string' && str && [\"'\", '\"'].indexOf(str.charAt(0)) !== -1\n  )\n}\n\nfunction hasLeadingNumber(part) {\n  return part.match(LEAD_DIGIT_REGEX) && !part.match(DIGIT_REGEX)\n}\n\nfunction hasSpecialChars(part) {\n  return SPEC_CHAR_REGEX.test(part)\n}\n\nfunction shouldBeQuoted(part) {\n  return !isQuoted(part) && (hasLeadingNumber(part) || hasSpecialChars(part))\n}\n",
      "start": 1702937442620,
      "end": 1702937442851,
      "sourcemaps": null
    },
    {
      "name": "vite:react-babel",
      "start": 1702937442851,
      "end": 1702937442851,
      "order": "pre"
    },
    {
      "name": "vite:css",
      "start": 1702937442851,
      "end": 1702937442851,
      "order": "normal"
    },
    {
      "name": "vite:esbuild",
      "start": 1702937442851,
      "end": 1702937442852,
      "order": "normal"
    },
    {
      "name": "vite:json",
      "start": 1702937442852,
      "end": 1702937442852,
      "order": "normal"
    },
    {
      "name": "vite:worker",
      "start": 1702937442852,
      "end": 1702937442852,
      "order": "normal"
    },
    {
      "name": "vite:define",
      "start": 1702937442852,
      "end": 1702937442852,
      "order": "normal"
    },
    {
      "name": "vite:css-post",
      "start": 1702937442852,
      "end": 1702937442852,
      "order": "normal"
    },
    {
      "name": "vite:build-html",
      "start": 1702937442852,
      "end": 1702937442852,
      "order": "normal"
    },
    {
      "name": "vite:worker-import-meta-url",
      "start": 1702937442852,
      "end": 1702937442852,
      "order": "normal"
    },
    {
      "name": "vite:asset-import-meta-url",
      "start": 1702937442852,
      "end": 1702937442852,
      "order": "normal"
    },
    {
      "name": "commonjs",
      "result": "/**\n * Based on Kendo UI Core expression code <https://github.com/telerik/kendo-ui-core#license-information>\n */\nimport * as commonjsHelpers from \"\u0000commonjsHelpers.js\";\n\n'use strict'\n\nfunction Cache(maxSize) {\n  this._maxSize = maxSize\n  this.clear()\n}\nCache.prototype.clear = function () {\n  this._size = 0\n  this._values = Object.create(null)\n}\nCache.prototype.get = function (key) {\n  return this._values[key]\n}\nCache.prototype.set = function (key, value) {\n  this._size >= this._maxSize && this.clear()\n  if (!(key in this._values)) this._size++\n\n  return (this._values[key] = value)\n}\n\nvar SPLIT_REGEX = /[^.^\\]^[]+|(?=\\[\\]|\\.\\.)/g,\n  DIGIT_REGEX = /^\\d+$/,\n  LEAD_DIGIT_REGEX = /^\\d/,\n  SPEC_CHAR_REGEX = /[~`!#$%\\^&*+=\\-\\[\\]\\\\';,/{}|\\\\\":<>\\?]/g,\n  CLEAN_QUOTES_REGEX = /^\\s*(['\"]?)(.*?)(\\1)\\s*$/,\n  MAX_CACHE_SIZE = 512\n\nvar pathCache = new Cache(MAX_CACHE_SIZE),\n  setCache = new Cache(MAX_CACHE_SIZE),\n  getCache = new Cache(MAX_CACHE_SIZE)\n\nvar config\n\nvar propertyExpr = {\n  Cache: Cache,\n\n  split: split,\n\n  normalizePath: normalizePath,\n\n  setter: function (path) {\n    var parts = normalizePath(path)\n\n    return (\n      setCache.get(path) ||\n      setCache.set(path, function setter(obj, value) {\n        var index = 0\n        var len = parts.length\n        var data = obj\n\n        while (index < len - 1) {\n          var part = parts[index]\n          if (\n            part === '__proto__' ||\n            part === 'constructor' ||\n            part === 'prototype'\n          ) {\n            return obj\n          }\n\n          data = data[parts[index++]]\n        }\n        data[parts[index]] = value\n      })\n    )\n  },\n\n  getter: function (path, safe) {\n    var parts = normalizePath(path)\n    return (\n      getCache.get(path) ||\n      getCache.set(path, function getter(data) {\n        var index = 0,\n          len = parts.length\n        while (index < len) {\n          if (data != null || !safe) data = data[parts[index++]]\n          else return\n        }\n        return data\n      })\n    )\n  },\n\n  join: function (segments) {\n    return segments.reduce(function (path, part) {\n      return (\n        path +\n        (isQuoted(part) || DIGIT_REGEX.test(part)\n          ? '[' + part + ']'\n          : (path ? '.' : '') + part)\n      )\n    }, '')\n  },\n\n  forEach: function (path, cb, thisArg) {\n    forEach(Array.isArray(path) ? path : split(path), cb, thisArg)\n  },\n}\n\nfunction normalizePath(path) {\n  return (\n    pathCache.get(path) ||\n    pathCache.set(\n      path,\n      split(path).map(function (part) {\n        return part.replace(CLEAN_QUOTES_REGEX, '$2')\n      })\n    )\n  )\n}\n\nfunction split(path) {\n  return path.match(SPLIT_REGEX) || ['']\n}\n\nfunction forEach(parts, iter, thisArg) {\n  var len = parts.length,\n    part,\n    idx,\n    isArray,\n    isBracket\n\n  for (idx = 0; idx < len; idx++) {\n    part = parts[idx]\n\n    if (part) {\n      if (shouldBeQuoted(part)) {\n        part = '\"' + part + '\"'\n      }\n\n      isBracket = isQuoted(part)\n      isArray = !isBracket && /^\\d+$/.test(part)\n\n      iter.call(thisArg, part, isBracket, isArray, idx, parts)\n    }\n  }\n}\n\nfunction isQuoted(str) {\n  return (\n    typeof str === 'string' && str && [\"'\", '\"'].indexOf(str.charAt(0)) !== -1\n  )\n}\n\nfunction hasLeadingNumber(part) {\n  return part.match(LEAD_DIGIT_REGEX) && !part.match(DIGIT_REGEX)\n}\n\nfunction hasSpecialChars(part) {\n  return SPEC_CHAR_REGEX.test(part)\n}\n\nfunction shouldBeQuoted(part) {\n  return !isQuoted(part) && (hasLeadingNumber(part) || hasSpecialChars(part))\n}\n\nexport default /*@__PURE__*/commonjsHelpers.getDefaultExportFromCjs(propertyExpr);\nexport { propertyExpr as __moduleExports };",
      "start": 1702937442852,
      "end": 1702937442852,
      "order": "normal",
      "sourcemaps": {
        "version": 3,
        "sources": [
          ""
        ],
        "names": [],
        "mappings": ";;;;;AAGA,YAAY;AACZ;AACA,SAAS,KAAK,CAAC,OAAO,EAAE;AACxB,EAAE,IAAI,CAAC,QAAQ,GAAG,OAAO;AACzB,EAAE,IAAI,CAAC,KAAK,EAAE;AACd,CAAC;AACD,KAAK,CAAC,SAAS,CAAC,KAAK,GAAG,YAAY;AACpC,EAAE,IAAI,CAAC,KAAK,GAAG,CAAC;AAChB,EAAE,IAAI,CAAC,OAAO,GAAG,MAAM,CAAC,MAAM,CAAC,IAAI,CAAC;AACpC,CAAC;AACD,KAAK,CAAC,SAAS,CAAC,GAAG,GAAG,UAAU,GAAG,EAAE;AACrC,EAAE,OAAO,IAAI,CAAC,OAAO,CAAC,GAAG,CAAC;AAC1B,CAAC;AACD,KAAK,CAAC,SAAS,CAAC,GAAG,GAAG,UAAU,GAAG,EAAE,KAAK,EAAE;AAC5C,EAAE,IAAI,CAAC,KAAK,IAAI,IAAI,CAAC,QAAQ,IAAI,IAAI,CAAC,KAAK,EAAE;AAC7C,EAAE,IAAI,EAAE,GAAG,IAAI,IAAI,CAAC,OAAO,CAAC,EAAE,IAAI,CAAC,KAAK,EAAE;AAC1C;AACA,EAAE,QAAQ,IAAI,CAAC,OAAO,CAAC,GAAG,CAAC,GAAG,KAAK,CAAC;AACpC,CAAC;AACD;AACA,IAAI,WAAW,GAAG,2BAA2B;AAC7C,EAAE,WAAW,GAAG,OAAO;AACvB,EAAE,gBAAgB,GAAG,KAAK;AAC1B,EAAE,eAAe,GAAG,wCAAwC;AAC5D,EAAE,kBAAkB,GAAG,0BAA0B;AACjD,EAAE,cAAc,GAAG,GAAG;AACtB;AACA,IAAI,SAAS,GAAG,IAAI,KAAK,CAAC,cAAc,CAAC;AACzC,EAAE,QAAQ,GAAG,IAAI,KAAK,CAAC,cAAc,CAAC;AACtC,EAAE,QAAQ,GAAG,IAAI,KAAK,CAAC,cAAc,CAAC;AACtC;AACA,IAAI,MAAM;AACV;IACA,YAAc,GAAG;AACjB,EAAE,KAAK,EAAE,KAAK;AACd;AACA,EAAE,KAAK,EAAE,KAAK;AACd;AACA,EAAE,aAAa,EAAE,aAAa;AAC9B;AACA,EAAE,MAAM,EAAE,UAAU,IAAI,EAAE;AAC1B,IAAI,IAAI,KAAK,GAAG,aAAa,CAAC,IAAI,CAAC;AACnC;AACA,IAAI;AACJ,MAAM,QAAQ,CAAC,GAAG,CAAC,IAAI,CAAC;AACxB,MAAM,QAAQ,CAAC,GAAG,CAAC,IAAI,EAAE,SAAS,MAAM,CAAC,GAAG,EAAE,KAAK,EAAE;AACrD,QAAQ,IAAI,KAAK,GAAG,CAAC;AACrB,QAAQ,IAAI,GAAG,GAAG,KAAK,CAAC,MAAM;AAC9B,QAAQ,IAAI,IAAI,GAAG,GAAG;AACtB;AACA,QAAQ,OAAO,KAAK,GAAG,GAAG,GAAG,CAAC,EAAE;AAChC,UAAU,IAAI,IAAI,GAAG,KAAK,CAAC,KAAK,CAAC;AACjC,UAAU;AACV,YAAY,IAAI,KAAK,WAAW;AAChC,YAAY,IAAI,KAAK,aAAa;AAClC,YAAY,IAAI,KAAK,WAAW;AAChC,YAAY;AACZ,YAAY,OAAO,GAAG;AACtB,WAAW;AACX;AACA,UAAU,IAAI,GAAG,IAAI,CAAC,KAAK,CAAC,KAAK,EAAE,CAAC,CAAC;AACrC,SAAS;AACT,QAAQ,IAAI,CAAC,KAAK,CAAC,KAAK,CAAC,CAAC,GAAG,KAAK;AAClC,OAAO,CAAC;AACR,KAAK;AACL,GAAG;AACH;AACA,EAAE,MAAM,EAAE,UAAU,IAAI,EAAE,IAAI,EAAE;AAChC,IAAI,IAAI,KAAK,GAAG,aAAa,CAAC,IAAI,CAAC;AACnC,IAAI;AACJ,MAAM,QAAQ,CAAC,GAAG,CAAC,IAAI,CAAC;AACxB,MAAM,QAAQ,CAAC,GAAG,CAAC,IAAI,EAAE,SAAS,MAAM,CAAC,IAAI,EAAE;AAC/C,QAAQ,IAAI,KAAK,GAAG,CAAC;AACrB,UAAU,GAAG,GAAG,KAAK,CAAC,MAAM;AAC5B,QAAQ,OAAO,KAAK,GAAG,GAAG,EAAE;AAC5B,UAAU,IAAI,IAAI,IAAI,IAAI,IAAI,CAAC,IAAI,EAAE,IAAI,GAAG,IAAI,CAAC,KAAK,CAAC,KAAK,EAAE,CAAC,CAAC;AAChE,eAAe,MAAM;AACrB,SAAS;AACT,QAAQ,OAAO,IAAI;AACnB,OAAO,CAAC;AACR,KAAK;AACL,GAAG;AACH;AACA,EAAE,IAAI,EAAE,UAAU,QAAQ,EAAE;AAC5B,IAAI,OAAO,QAAQ,CAAC,MAAM,CAAC,UAAU,IAAI,EAAE,IAAI,EAAE;AACjD,MAAM;AACN,QAAQ,IAAI;AACZ,SAAS,QAAQ,CAAC,IAAI,CAAC,IAAI,WAAW,CAAC,IAAI,CAAC,IAAI,CAAC;AACjD,YAAY,GAAG,GAAG,IAAI,GAAG,GAAG;AAC5B,YAAY,CAAC,IAAI,GAAG,GAAG,GAAG,EAAE,IAAI,IAAI,CAAC;AACrC,OAAO;AACP,KAAK,EAAE,EAAE,CAAC;AACV,GAAG;AACH;AACA,EAAE,OAAO,EAAE,UAAU,IAAI,EAAE,EAAE,EAAE,OAAO,EAAE;AACxC,IAAI,OAAO,CAAC,KAAK,CAAC,OAAO,CAAC,IAAI,CAAC,GAAG,IAAI,GAAG,KAAK,CAAC,IAAI,CAAC,EAAE,EAAE,EAAE,OAAO,CAAC;AAClE,GAAG;AACH,CAAC;AACD;AACA,SAAS,aAAa,CAAC,IAAI,EAAE;AAC7B,EAAE;AACF,IAAI,SAAS,CAAC,GAAG,CAAC,IAAI,CAAC;AACvB,IAAI,SAAS,CAAC,GAAG;AACjB,MAAM,IAAI;AACV,MAAM,KAAK,CAAC,IAAI,CAAC,CAAC,GAAG,CAAC,UAAU,IAAI,EAAE;AACtC,QAAQ,OAAO,IAAI,CAAC,OAAO,CAAC,kBAAkB,EAAE,IAAI,CAAC;AACrD,OAAO,CAAC;AACR,KAAK;AACL,GAAG;AACH,CAAC;AACD;AACA,SAAS,KAAK,CAAC,IAAI,EAAE;AACrB,EAAE,OAAO,IAAI,CAAC,KAAK,CAAC,WAAW,CAAC,IAAI,CAAC,EAAE,CAAC;AACxC,CAAC;AACD;AACA,SAAS,OAAO,CAAC,KAAK,EAAE,IAAI,EAAE,OAAO,EAAE;AACvC,EAAE,IAAI,GAAG,GAAG,KAAK,CAAC,MAAM;AACxB,IAAI,IAAI;AACR,IAAI,GAAG;AACP,IAAI,OAAO;AACX,IAAI,SAAS;AACb;AACA,EAAE,KAAK,GAAG,GAAG,CAAC,EAAE,GAAG,GAAG,GAAG,EAAE,GAAG,EAAE,EAAE;AAClC,IAAI,IAAI,GAAG,KAAK,CAAC,GAAG,CAAC;AACrB;AACA,IAAI,IAAI,IAAI,EAAE;AACd,MAAM,IAAI,cAAc,CAAC,IAAI,CAAC,EAAE;AAChC,QAAQ,IAAI,GAAG,GAAG,GAAG,IAAI,GAAG,GAAG;AAC/B,OAAO;AACP;AACA,MAAM,SAAS,GAAG,QAAQ,CAAC,IAAI,CAAC;AAChC,MAAM,OAAO,GAAG,CAAC,SAAS,IAAI,OAAO,CAAC,IAAI,CAAC,IAAI,CAAC;AAChD;AACA,MAAM,IAAI,CAAC,IAAI,CAAC,OAAO,EAAE,IAAI,EAAE,SAAS,EAAE,OAAO,EAAE,GAAG,EAAE,KAAK,CAAC;AAC9D,KAAK;AACL,GAAG;AACH,CAAC;AACD;AACA,SAAS,QAAQ,CAAC,GAAG,EAAE;AACvB,EAAE;AACF,IAAI,OAAO,GAAG,KAAK,QAAQ,IAAI,GAAG,IAAI,CAAC,GAAG,EAAE,GAAG,CAAC,CAAC,OAAO,CAAC,GAAG,CAAC,MAAM,CAAC,CAAC,CAAC,CAAC,KAAK,CAAC,CAAC;AAC9E,GAAG;AACH,CAAC;AACD;AACA,SAAS,gBAAgB,CAAC,IAAI,EAAE;AAChC,EAAE,OAAO,IAAI,CAAC,KAAK,CAAC,gBAAgB,CAAC,IAAI,CAAC,IAAI,CAAC,KAAK,CAAC,WAAW,CAAC;AACjE,CAAC;AACD;AACA,SAAS,eAAe,CAAC,IAAI,EAAE;AAC/B,EAAE,OAAO,eAAe,CAAC,IAAI,CAAC,IAAI,CAAC;AACnC,CAAC;AACD;AACA,SAAS,cAAc,CAAC,IAAI,EAAE;AAC9B,EAAE,OAAO,CAAC,QAAQ,CAAC,IAAI,CAAC,KAAK,gBAAgB,CAAC,IAAI,CAAC,IAAI,eAAe,CAAC,IAAI,CAAC,CAAC;AAC7E"
      }
    },
    {
      "name": "inject",
      "start": 1702937442853,
      "end": 1702937442853,
      "order": "normal"
    },
    {
      "name": "vite:dynamic-import-vars",
      "start": 1702937442853,
      "end": 1702937442853,
      "order": "normal"
    },
    {
      "name": "vite:import-glob",
      "start": 1702937442853,
      "end": 1702937442853,
      "order": "normal"
    },
    {
      "name": "vite:build-import-analysis",
      "start": 1702937442853,
      "end": 1702937442853,
      "order": "normal"
    },
    {
      "name": "vite:reporter",
      "start": 1702937442853,
      "end": 1702937442853,
      "order": "normal"
    }
  ]
}
